backkr/__init__.py
backkr/cli.py
backkr/http.py
backkr/paginations.py
backkr/template.py
backkr/urls.py
backkr/middlewares/__init__.py
backkr-0.0.4.dist-info/LICENSE
backkr-0.0.4.dist-info/METADATA
backkr-0.0.4.dist-info/WHEEL
backkr-0.0.4.dist-info/entry_points.txt
backkr-0.0.4.dist-info/top_level.txt
backkr-0.0.4.dist-info/RECORD
