Metadata-Version: 2.1
Name: backkr
Version: 0.0.4
Summary: A backend framework the web
Home-page: https://github.com/Almas-Ali/backkr
Author: Almas Ali
Author-email: almaspr3@gmail.com
Keywords: web framework
Classifier: Development Status :: 2 - Pre-Alpha
Classifier: Intended Audience :: Developers
Classifier: License :: OSI Approved :: MIT License
Classifier: Programming Language :: Python :: 3.7
Classifier: Programming Language :: Python :: 3.8
Classifier: Programming Language :: Python :: 3.9
Classifier: Programming Language :: Python :: 3.10
Classifier: Programming Language :: Python :: 3.11
Requires-Python: >=3.10
License-File: LICENSE
Requires-Dist: aiohttp
Requires-Dist: watchdog
